robustgp/__init__.py
robustgp/robustgp.py
robustgp-2.1.dist-info/LICENSE
robustgp-2.1.dist-info/METADATA
robustgp-2.1.dist-info/WHEEL
robustgp-2.1.dist-info/top_level.txt
robustgp-2.1.dist-info/RECORD
