Metadata-Version: 2.1
Name: robustgp
Version: 2.1
Summary: Robust Gaussian process regression based on iterative trimming.
Home-page: https://github.com/syrte/robustgp/
Author: Zhaozhou Li
Author-email: styr.py@gmail.com
License: UNKNOWN
Keywords: Gaussian process,regression,robust statistics,outlier detection
Platform: UNKNOWN
Classifier: Development Status :: 4 - Beta
Classifier: Topic :: Scientific/Engineering
Classifier: License :: OSI Approved :: MIT License
Classifier: Programming Language :: Python :: 3
Requires-Dist: gpy
